apply_async/__init__.py
apply_async-0.1.2.dist-info/WHEEL
apply_async-0.1.2.dist-info/METADATA
apply_async-0.1.2.dist-info/RECORD
