Metadata-Version: 2.1
Name: apply-async
Version: 0.1.2
Summary: 
Author: Jeff Shen
Author-email: shenjeff@princeton.edu
Requires-Python: >=3.10,<4.0
Classifier: Programming Language :: Python :: 3
Classifier: Programming Language :: Python :: 3.10
Classifier: Programming Language :: Python :: 3.11
Requires-Dist: multiprocess (>=0.70.14,<0.71.0)
Requires-Dist: rich (>=13.3.3,<14.0.0)
